{"description":"should display options for Bank Manager|Login","passed":false,"pending":false,"os":"Windows NT","instanceId":20828,"browser":{"name":"chrome","version":"69.0.3497.100"},"message":["Failed: Cannot read property 'isDisplayed' of undefined"],"trace":["TypeError: Cannot read property 'isDisplayed' of undefined\n    at UserContext.it (C:\\Users\\aydan\\OneDrive\\Desktop\\C_tek\\CyberFramework\\CyberBank\\Tests\\BankManagerSimple.spec.js:43:42)\n    at C:\\Users\\aydan\\AppData\\Roaming\\npm\\node_modules\\protractor\\node_modules\\jasminewd2\\index.js:112:25\n    at new ManagedPromise (C:\\Users\\aydan\\AppData\\Roaming\\npm\\node_modules\\protractor\\node_modules\\selenium-webdriver\\lib\\promise.js:1077:7)\n    at ControlFlow.promise (C:\\Users\\aydan\\AppData\\Roaming\\npm\\node_modules\\protractor\\node_modules\\selenium-webdriver\\lib\\promise.js:2505:12)\n    at schedulerExecute (C:\\Users\\aydan\\AppData\\Roaming\\npm\\node_modules\\protractor\\node_modules\\jasminewd2\\index.js:95:18)\n    at TaskQueue.execute_ (C:\\Users\\aydan\\AppData\\Roaming\\npm\\node_modules\\protractor\\node_modules\\selenium-webdriver\\lib\\promise.js:3084:14)\n    at TaskQueue.executeNext_ (C:\\Users\\aydan\\AppData\\Roaming\\npm\\node_modules\\protractor\\node_modules\\selenium-webdriver\\lib\\promise.js:3067:27)\n    at asyncRun (C:\\Users\\aydan\\AppData\\Roaming\\npm\\node_modules\\protractor\\node_modules\\selenium-webdriver\\lib\\promise.js:2974:25)\n    at C:\\Users\\aydan\\AppData\\Roaming\\npm\\node_modules\\protractor\\node_modules\\selenium-webdriver\\lib\\promise.js:668:7\n    at <anonymous>\nFrom: Task: Run it(\"should display options for Bank Manager\") in control flow\n    at UserContext.<anonymous> (C:\\Users\\aydan\\AppData\\Roaming\\npm\\node_modules\\protractor\\node_modules\\jasminewd2\\index.js:94:19)\n    at attempt (C:\\Users\\aydan\\AppData\\Roaming\\npm\\node_modules\\protractor\\node_modules\\jasmine-core\\lib\\jasmine-core\\jasmine.js:4297:26)\n    at QueueRunner.run (C:\\Users\\aydan\\AppData\\Roaming\\npm\\node_modules\\protractor\\node_modules\\jasmine-core\\lib\\jasmine-core\\jasmine.js:4217:20)\n    at runNext (C:\\Users\\aydan\\AppData\\Roaming\\npm\\node_modules\\protractor\\node_modules\\jasmine-core\\lib\\jasmine-core\\jasmine.js:4257:20)\n    at C:\\Users\\aydan\\AppData\\Roaming\\npm\\node_modules\\protractor\\node_modules\\jasmine-core\\lib\\jasmine-core\\jasmine.js:4264:13\n    at C:\\Users\\aydan\\AppData\\Roaming\\npm\\node_modules\\protractor\\node_modules\\jasmine-core\\lib\\jasmine-core\\jasmine.js:4172:9\n    at C:\\Users\\aydan\\AppData\\Roaming\\npm\\node_modules\\protractor\\node_modules\\jasminewd2\\index.js:64:48\n    at ControlFlow.emit (C:\\Users\\aydan\\AppData\\Roaming\\npm\\node_modules\\protractor\\node_modules\\selenium-webdriver\\lib\\events.js:62:21)\n    at ControlFlow.shutdown_ (C:\\Users\\aydan\\AppData\\Roaming\\npm\\node_modules\\protractor\\node_modules\\selenium-webdriver\\lib\\promise.js:2674:10)\n    at shutdownTask_.MicroTask (C:\\Users\\aydan\\AppData\\Roaming\\npm\\node_modules\\protractor\\node_modules\\selenium-webdriver\\lib\\promise.js:2599:53)\nFrom asynchronous test: \nError\n    at Suite.describe (C:\\Users\\aydan\\OneDrive\\Desktop\\C_tek\\CyberFramework\\CyberBank\\Tests\\BankManagerSimple.spec.js:39:5)\n    at addSpecsToSuite (C:\\Users\\aydan\\AppData\\Roaming\\npm\\node_modules\\protractor\\node_modules\\jasmine-core\\lib\\jasmine-core\\jasmine.js:1107:25)\n    at Env.describe (C:\\Users\\aydan\\AppData\\Roaming\\npm\\node_modules\\protractor\\node_modules\\jasmine-core\\lib\\jasmine-core\\jasmine.js:1074:7)\n    at describe (C:\\Users\\aydan\\AppData\\Roaming\\npm\\node_modules\\protractor\\node_modules\\jasmine-core\\lib\\jasmine-core\\jasmine.js:4399:18)\n    at Object.<anonymous> (C:\\Users\\aydan\\OneDrive\\Desktop\\C_tek\\CyberFramework\\CyberBank\\Tests\\BankManagerSimple.spec.js:8:1)\n    at Module._compile (module.js:653:30)\n    at Object.Module._extensions..js (module.js:664:10)\n    at Module.load (module.js:566:32)\n    at tryModuleLoad (module.js:506:12)"],"browserLogs":[],"screenShotFile":"images\\00050026-00cf-0009-008f-002100b4002b.png","timestamp":1539552232951,"duration":843}
